LICENSE
README.md
setup.py
saconfig/__init__.py
saconfig/base.py
saconfig/configs.py
saconfig/django.py
saconfig/exceptions.py
saconfig/parsers.py
saconfig/transformers.py
saconfig.egg-info/PKG-INFO
saconfig.egg-info/SOURCES.txt
saconfig.egg-info/dependency_links.txt
saconfig.egg-info/top_level.txt