Metadata-Version: 2.1
Name: saconfig
Version: 0.0.2
Summary: Flexible config module to manage env variables
Author: Sidq
Author-email: abba.dmytro@gmail.com
License:                                  Apache License
Project-URL: GitHub, https://github.com/sidqdev/saconfig
Project-URL: Telegram, https://t.me/sidqdev
Classifier: Programming Language :: Python :: 3
Classifier: Operating System :: OS Independent
Requires-Python: >=3.6
License-File: LICENSE
